ryven/__init__.py
ryven/gui_env.py
ryven/node_env.py
ryven/example_nodes/OpenCV/README.md
ryven/example_nodes/OpenCV/nodes.py
ryven/example_nodes/OpenCV/widgets.py
ryven/example_nodes/examples/README.md
ryven/example_nodes/examples/__init__.py
ryven/example_nodes/examples/basic_operators.py
ryven/example_nodes/examples/control_structures.py
ryven/example_nodes/examples/gui.py
ryven/example_nodes/examples/nodes.py
ryven/example_nodes/examples/special_nodes.py
ryven/example_nodes/inspector_example/__init__.py
ryven/example_nodes/inspector_example/gui.py
ryven/example_nodes/inspector_example/nodes.py
ryven/example_nodes/linalg/README.md
ryven/example_nodes/linalg/__init__.py
ryven/example_nodes/linalg/gui.py
ryven/example_nodes/linalg/matrices.py
ryven/example_nodes/linalg/nodes.py
ryven/example_projects/basics.json
ryven/example_projects/matrices.json
ryven/gui/__init__.py
ryven/gui/dialogs.py
ryven/gui/flow_ui.py
ryven/gui/main_console.py
ryven/gui/main_window.py
ryven/gui/std_input_widgets.py
ryven/gui/code_editor/CodeEditorWidget.py
ryven/gui/code_editor/CodePreviewWidget.py
ryven/gui/code_editor/EditSrcCodeInfoDialog.py
ryven/gui/code_editor/SourceCodeUpdater.py
ryven/gui/code_editor/__init__.py
ryven/gui/code_editor/codes_storage.py
ryven/gui/code_editor/pygments/__init__.py
ryven/gui/code_editor/pygments/dracula.py
ryven/gui/code_editor/pygments/light.py
ryven/gui/startup_dialog/StartupDialog.py
ryven/gui/startup_dialog/__init__.py
ryven/gui/styling/__init__.py
ryven/gui/styling/design_config.json
ryven/gui/styling/window_theme.py
ryven/gui/uic/__init__.py
ryven/gui/uic/flow.ui
ryven/gui/uic/flow_window.ui
ryven/gui/uic/main_window.ui
ryven/gui/uic/ui_flow.py
ryven/gui/uic/ui_flow_window.py
ryven/gui/uic/ui_main_window.py
ryven/main/Ryven.py
ryven/main/RyvenConsole.py
ryven/main/__init__.py
ryven/main/args_parser.py
ryven/main/config.py
ryven/main/utils.py
ryven/main/packages/__init__.py
ryven/main/packages/gui_env.py
ryven/main/packages/node_env.py
ryven-3.5.0.dist-info/LICENSE
ryven-3.5.0.dist-info/METADATA
ryven-3.5.0.dist-info/WHEEL
ryven-3.5.0.dist-info/entry_points.txt
ryven-3.5.0.dist-info/top_level.txt
ryven-3.5.0.dist-info/RECORD
