Metadata-Version: 2.1
Name: ryven
Version: 3.5.0
Summary: Flow-based visual scripting for Python
Home-page: https://github.com/leon-thomm/Ryven
Author: Leon Thomm
Author-email: l.thomm@mailbox.org
Project-URL: Website, https://ryven.org
Classifier: Programming Language :: Python :: 3
Classifier: License :: OSI Approved :: MIT License
Classifier: Operating System :: OS Independent
Requires-Python: <3.13,>=3.6
License-File: LICENSE
Requires-Dist: ryvencore-qt ==0.5.*
Requires-Dist: ryvencore ==0.5.*
Requires-Dist: Jinja2
Requires-Dist: Pygments
Requires-Dist: textdistance
Requires-Dist: packaging
